setup.py
nbupload/FileUploaderView.js
nbupload/FileUploaderWidget.py
nbupload/__init__.py
nbupload.egg-info/PKG-INFO
nbupload.egg-info/SOURCES.txt
nbupload.egg-info/dependency_links.txt
nbupload.egg-info/top_level.txt