Metadata-Version: 1.0
Name: nbupload
Version: 0.0.3
Summary: An IPython Notebook widget for letting users upload a file
Home-page: https://github.com/edvakf/nbupload
Author: Atsushi Takayama
Author-email: taka.atsushi@gmail.com
License: MIT
Keywords: ipython notebook
Platform: UNKNOWN
